thima/__init__.py
thima/module1.py
thima/module2.py
thima/test.py
thima-0.0.1.dist-info/LICENSE.txt
thima-0.0.1.dist-info/METADATA
thima-0.0.1.dist-info/WHEEL
thima-0.0.1.dist-info/top_level.txt
thima-0.0.1.dist-info/RECORD
